Metadata-Version: 2.1
Name: superglobals
Version: 0.0.16
Summary: globals() access anywhere. "We Do Anything, Anytime"
Home-page: https://github.com/sfinktah/superglobals
Author: Christopher Anderson
Author-email: sfinktah@github.spamtrak.org
License: MIT
Platform: UNKNOWN
Classifier: Programming Language :: Python :: 3
Classifier: Programming Language :: Python :: 2
Classifier: License :: OSI Approved :: MIT License
Classifier: Operating System :: OS Independent
Requires-Python: >=2.7
License-File: LICENSE.txt
